{
  "project_info": {
    "project_number": "513035274437",
    "project_id": "islam786-d051e",
    "storage_bucket": "islam786-d051e.appspot.com"
  },
  "client": [
    {
      "client_info": {
        "mobilesdk_app_id": "1:513035274437:android:9c841d504971752edbc8ac",
        "android_client_info": {
          "package_name": "com.hellodearcode.islam786"
        }
      },
      "oauth_client": [
        {
          "client_id": "513035274437-qdvrmsfpqddfceqq9e2u2da6avjlgqim.apps.googleusercontent.com",
          "client_type": 1,
          "android_info": {
            "package_name": "com.hellodearcode.islam786",
            "certificate_hash": "5cb6fa578386bd37626a57b5942da39c567ddcf8"
          }
        },
        {
          "client_id": "513035274437-uu9ugihuo66e3rftg56f517d0e9o0ed2.apps.googleusercontent.com",
          "client_type": 1,
          "android_info": {
            "package_name": "com.hellodearcode.islam786",
            "certificate_hash": "55f9188afe676a4b02badd8bbeeece57f6e83ae3"
          }
        },
        {
          "client_id": "513035274437-adcn400jeb28q5qomafpnte7av109q6h.apps.googleusercontent.com",
          "client_type": 3
        }
      ],
      "api_key": [
        {
          "current_key": "AIzaSyAiQlA00CxmLHeOYuZmHrWFutSk1Np_zgg"
        }
      ],
      "services": {
        "appinvite_service": {
          "other_platform_oauth_client": [
            {
              "client_id": "513035274437-adcn400jeb28q5qomafpnte7av109q6h.apps.googleusercontent.com",
              "client_type": 3
            }
          ]
        }
      }
    }
  ],
  "configuration_version": "1"
}